pyxing/__init__.py
pyxing/ddec.py
pyxing/query.py
pyxing/real.py
pyxing/res.py
pyxing/session.py
pyxing-0.0.5.dist-info/LICENSE
pyxing-0.0.5.dist-info/METADATA
pyxing-0.0.5.dist-info/WHEEL
pyxing-0.0.5.dist-info/top_level.txt
pyxing-0.0.5.dist-info/RECORD
