Metadata-Version: 2.1
Name: pyxing
Version: 0.0.5
Summary: python wrapper for eBest Xing API
Home-page: https://github.com/sharebook-kr/pyxing
Author: Lukas Yoo, Brayden Jo
Author-email: jonghun.yoo@outlook.com, brayden.jo@outlook.com, pystock@outlook.com
License: MIT
Platform: UNKNOWN
Requires-Dist: pandas
